fucckker/__init__.py
fucckker/wp.py
fucckker-1.0.dist-info/LICENSE
fucckker-1.0.dist-info/METADATA
fucckker-1.0.dist-info/WHEEL
fucckker-1.0.dist-info/top_level.txt
fucckker-1.0.dist-info/RECORD
