Metadata-Version: 2.1
Name: fucckker
Version: 1.0
Summary: 一个非常NB的包
Author: chenshaoyu
Author-email: 18104602153@163.com
Classifier: Programming Language :: Python :: 3
Classifier: License :: OSI Approved :: MIT License
Classifier: Operating System :: OS Independent
Requires-Python: >=3
License-File: LICENSE
Requires-Dist: pillow
